helper_scripts/__init__.py
helper_scripts/assign_fixed_chains.py
helper_scripts/make_bias_AA.py
helper_scripts/make_bias_per_res_dict.py
helper_scripts/make_fixed_positions_dict.py
helper_scripts/make_pos_neg_tied_positions_dict.py
helper_scripts/make_pssm_input_dict.py
helper_scripts/make_tied_positions_dict.py
helper_scripts/parse_multiple_chains.py
proteinmpnn/__init__.py
proteinmpnn/protein_mpnn_run.py
proteinmpnn/protein_mpnn_utils.py
proteinmpnn/data/__init__.py
proteinmpnn/data/ca_model_weights/__init__.py
proteinmpnn/data/ca_model_weights/v_48_002.pt
proteinmpnn/data/ca_model_weights/v_48_010.pt
proteinmpnn/data/ca_model_weights/v_48_020.pt
proteinmpnn/data/soluble_model_weights/__init__.py
proteinmpnn/data/soluble_model_weights/v_48_002.pt
proteinmpnn/data/soluble_model_weights/v_48_010.pt
proteinmpnn/data/soluble_model_weights/v_48_020.pt
proteinmpnn/data/soluble_model_weights/v_48_030.pt
proteinmpnn/data/vanilla_model_weights/__init__.py
proteinmpnn/data/vanilla_model_weights/v_48_002.pt
proteinmpnn/data/vanilla_model_weights/v_48_010.pt
proteinmpnn/data/vanilla_model_weights/v_48_020.pt
proteinmpnn/data/vanilla_model_weights/v_48_030.pt
proteinmpnn-0.1.3.dist-info/licenses/LICENSE
proteinmpnn-0.1.3.dist-info/METADATA
proteinmpnn-0.1.3.dist-info/WHEEL
proteinmpnn-0.1.3.dist-info/entry_points.txt
proteinmpnn-0.1.3.dist-info/top_level.txt
proteinmpnn-0.1.3.dist-info/RECORD
