Metadata-Version: 2.4
Name: proteinmpnn
Version: 0.1.3
Summary: a slightly cleaned up installable version of ProteinMPNN
Home-page: https://github.com/Markusjsommer/ProteinMPNN
Author: originally and primarily authored by Justas Dauparas. installable version by markus.
Author-email: installable: markusjsommer@gmail.com ; original: justas@uw.edu
License: MIT
Classifier: License :: OSI Approved :: MIT License
Classifier: Programming Language :: Python :: 3.11
Classifier: Operating System :: POSIX :: Linux
Classifier: Operating System :: MacOS :: MacOS X
Requires-Python: >=3.9, <3.13
License-File: LICENSE
Requires-Dist: torch>=2.1.2
Requires-Dist: torchvision>=0.16.2
Requires-Dist: torchaudio>=2.1.2
Requires-Dist: typing-extensions>=4.9.0
Requires-Dist: numpy<2,>=1.24.4
Requires-Dist: setuptools
Provides-Extra: dev
Requires-Dist: pytest>=7.0; extra == "dev"
Requires-Dist: twine>=4.0.2; extra == "dev"
Requires-Dist: pytest-cov>=4.0; extra == "dev"
Requires-Dist: wheel; extra == "dev"
Dynamic: author
Dynamic: author-email
Dynamic: classifier
Dynamic: description
Dynamic: description-content-type
Dynamic: home-page
Dynamic: license
Dynamic: license-file
Dynamic: provides-extra
Dynamic: requires-dist
Dynamic: requires-python
Dynamic: summary
